adif_file/__init__.py
adif_file/__version__.py
adif_file/adi.py
adif_file/adx.py
adif_file/util.py
adif_file/xsd/adx314.xsd
adif_file/xsd/adx314generic.xsd
pyadif_file-1.3.2.dist-info/licenses/LICENSE
pyadif_file-1.3.2.dist-info/METADATA
pyadif_file-1.3.2.dist-info/WHEEL
pyadif_file-1.3.2.dist-info/top_level.txt
pyadif_file-1.3.2.dist-info/RECORD
