Metadata-Version: 2.4
Name: PyADIF-File
Version: 1.3.2
Summary: Convert ADIF ADI/ADX content to dictionary and vice versa
Author-email: "Andreas Schawo, DF1ASC" <andreas@schawo.de>
Project-URL: Homepage, https://github.com/gitandy/PyADIF-File#pyadif-file
Project-URL: Bug Tracker, https://github.com/gitandy/PyADIF-File/issues
Classifier: Development Status :: 5 - Production/Stable
Classifier: Intended Audience :: Developers
Classifier: Operating System :: OS Independent
Classifier: Programming Language :: Python :: 3 :: Only
Classifier: Programming Language :: Python :: 3.9
Classifier: Programming Language :: Python :: 3.10
Classifier: Programming Language :: Python :: 3.11
Classifier: Programming Language :: Python :: 3.12
Classifier: Topic :: Communications :: Ham Radio
Classifier: Topic :: File Formats
Classifier: Topic :: Software Development :: Libraries
Classifier: Topic :: Software Development :: Libraries :: Python Modules
Requires-Python: >=3.9
License-File: LICENSE
Requires-Dist: xmlschema
Requires-Dist: xmltodict
Dynamic: license-file
